mm_pal/__init__.py
mm_pal/conformance_test.py
mm_pal/misc.py
mm_pal/mm_cmd.py
mm_pal/mm_if.py
mm_pal/serial_driver.py
mock_pal/__init__.py
mock_pal/mock_cli.py
mock_pal/mock_dev.py
mock_pal/mock_if.py
mock_pal/mem_map/example_map_config.json
mock_pal/mem_map/example_map_t_0_0_1.csv
mm_pal-1.2.1.dist-info/LICENSE
mm_pal-1.2.1.dist-info/METADATA
mm_pal-1.2.1.dist-info/WHEEL
mm_pal-1.2.1.dist-info/entry_points.txt
mm_pal-1.2.1.dist-info/top_level.txt
mm_pal-1.2.1.dist-info/RECORD
