Metadata-Version: 2.1
Name: mm-pal
Version: 1.2.1
Summary: Protocol abstraction and parser for embedded devices
Home-page: https://github.com/riot-appstore
Author: Kevin Weiss
Author-email: weiss.kevin604@gmail.com
License: MIT
Platform: any
Classifier: License :: OSI Approved :: MIT License
Classifier: Operating System :: OS Independent
Classifier: Development Status :: 3 - Alpha
Classifier: Programming Language :: Python
Classifier: Programming Language :: Python :: 3
Classifier: Programming Language :: Python :: 3.7
Classifier: Programming Language :: Python :: 3.8
Classifier: Programming Language :: Python :: 3.9
Classifier: Programming Language :: Python :: 3.10
Classifier: Intended Audience :: Developers
Requires-Python: >=3.7.*
Requires-Dist: pyserial
Requires-Dist: cmd2 (>=2)
